sociallib/__init__.py
sociallib/__main__.py
sociallib/addition_tools.py
sociallib/color_codes.py
sociallib/constants.py
sociallib/errors.py
sociallib/libapi.py
sociallib/models.py
sociallib/novelTypes.py
sociallib/server_constants.py
sociallib_py-0.0.1.dist-info/licenses/LICENSE
sociallib_py-0.0.1.dist-info/METADATA
sociallib_py-0.0.1.dist-info/WHEEL
sociallib_py-0.0.1.dist-info/top_level.txt
sociallib_py-0.0.1.dist-info/RECORD
